{
  "name": "@vielzeug/keymap",
  "entries": [
    {
      "version": "1.0.1",
      "tag": "@vielzeug/keymap_v1.0.1",
      "date": "Fri, 03 Jul 2026 06:00:47 GMT",
      "comments": {
        "patch": [
          {
            "comment": "chore(keymap): rename internal _warn.ts to _dev.ts",
            "author": "Helmuth Saatkamp <helmuthdu@gmail.com>",
            "commit": "1b696f77f93b469187d4d7bae13012812a126885"
          }
        ]
      }
    },
    {
      "version": "1.0.0",
      "tag": "@vielzeug/keymap_v1.0.0",
      "date": "Wed, 01 Jul 2026 16:10:37 GMT",
      "comments": {
        "major": [
          {
            "comment": "Initial public release",
            "author": "Helmuth Saatkamp <helmuthdu@gmail.com>",
            "commit": "f5090bdde453be839b7dff39679a9e89510cb0dd"
          }
        ]
      }
    }
  ]
}
